pyhound-0.1.0.dist-info/entry_points.txt
pyhound-0.1.0.dist-info/top_level.txt
pyhound-0.1.0.dist-info/WHEEL
pyhound-0.1.0.dist-info/DESCRIPTION.rst
pyhound-0.1.0.dist-info/METADATA
pyhound-0.1.0.dist-info/RECORD
pyhound-0.1.0.dist-info/metadata.json
tests/test_hound.py
tests/__init__.py
pyhound/__init__.py
pyhound/version.py
pyhound/hound.py
pyhound/cli.py
