Metadata-Version: 2.0
Name: pyhound
Version: 0.1.0
Summary: A command-line client for the Hound source code search engine.
Home-page: UNKNOWN
Author: Polyconseil
Author-email: opensource+pyhound@polyconseil.fr
License: UNKNOWN
Keywords: hound client source code search
Platform: UNKNOWN
Classifier: Development Status :: 4 - Beta
Classifier: Environment :: Console
Classifier: Intended Audience :: Developers
Classifier: License :: OSI Approved :: BSD License
Classifier: Natural Language :: English
Classifier: Programming Language :: Python
Classifier: Programming Language :: Python :: 2.6
Classifier: Programming Language :: Python :: 2.7
Classifier: Programming Language :: Python :: 3
Classifier: Programming Language :: Python :: 3.3
Classifier: Programming Language :: Python :: 3.4
Classifier: Topic :: Software Development
Requires-Dist: requests (==2.5.1)
Requires-Dist: argparse; python_version=="2.6"
